LICENSE
MANIFEST.in
README.rst
setup.cfg
setup.py
model_organization/__init__.py
model_organization/__main__.py
model_organization/config.py
model_organization/utils.py
model_organization.egg-info/PKG-INFO
model_organization.egg-info/SOURCES.txt
model_organization.egg-info/dependency_links.txt
model_organization.egg-info/not-zip-safe
model_organization.egg-info/requires.txt
model_organization.egg-info/top_level.txt