Metadata-Version: 1.1
Name: model-organization
Version: 0.1.10
Summary: Organize your computational models transparently
Home-page: https://github.com/Chilipp/model-organization
Author: Philipp Sommer
Author-email: philipp.sommer@unil.ch
License: GPLv2
Keywords: climate model framework
Platform: UNKNOWN
Classifier: Development Status :: 5 - Production/Stable
Classifier: Intended Audience :: Developers
Classifier: Topic :: Documentation
Classifier: License :: OSI Approved :: GNU General Public License v2 (GPLv2)
Classifier: Programming Language :: Python :: 2
Classifier: Programming Language :: Python :: 2.7
Classifier: Programming Language :: Python :: 3
Classifier: Programming Language :: Python :: 3.5
Classifier: Programming Language :: Python :: 3.6
Classifier: Operating System :: OS Independent
